table_utils
