Metadata-Version: 2.1
Name: table-utils
Version: 0.0.3
Summary: table utils
Home-page: 
Author: zbc
Author-email: zbc@mail.ustc.edu.cn
License: UNKNOWN
Platform: UNKNOWN
Classifier: Programming Language :: Python :: 3
Classifier: License :: OSI Approved :: MIT License
Classifier: Operating System :: OS Independent
Requires-Python: >=3.5
